auth/__init__.py
auth/api.py
auth/factories.py
auth/models.py
auth/plugin.py
auth/services.py
core/cli.py
core/database.py
core/openapi.py
core/settings.py
service_laboratory-4.0.6.dist-info/METADATA
service_laboratory-4.0.6.dist-info/WHEEL
service_laboratory-4.0.6.dist-info/licenses/LICENSE.txt
service_laboratory-4.0.6.dist-info/RECORD
